saola_graphql_client/__init__.py
saola_graphql_client/graphql_client/__init__.py
saola_graphql_client/graphql_client/async_base_client.py
saola_graphql_client/graphql_client/base_model.py
saola_graphql_client/graphql_client/client.py
saola_graphql_client/graphql_client/enums.py
saola_graphql_client/graphql_client/exceptions.py
saola_graphql_client/graphql_client/fragments.py
saola_graphql_client/graphql_client/get_active_connections.py
saola_graphql_client/graphql_client/get_chat.py
saola_graphql_client/graphql_client/get_chat_crm_records.py
saola_graphql_client/graphql_client/get_chats.py
saola_graphql_client/graphql_client/get_chats_by_status.py
saola_graphql_client/graphql_client/get_connection.py
saola_graphql_client/graphql_client/get_crm_record.py
saola_graphql_client/graphql_client/get_source.py
saola_graphql_client/graphql_client/get_source_chats.py
saola_graphql_client/graphql_client/get_user.py
saola_graphql_client/graphql_client/get_workspace.py
saola_graphql_client/graphql_client/get_workspace_connections.py
saola_graphql_client/graphql_client/get_workspace_sources.py
saola_graphql_client/graphql_client/get_workspaces.py
saola_graphql_client/graphql_client/input_types.py
saola_graphql_client/graphql_client/refresh_access_token.py
saola_graphql_client/graphql_client/sign_out.py
saola_graphql_client-0.0.8.dist-info/LICENSE.md
saola_graphql_client-0.0.8.dist-info/METADATA
saola_graphql_client-0.0.8.dist-info/WHEEL
saola_graphql_client-0.0.8.dist-info/top_level.txt
saola_graphql_client-0.0.8.dist-info/RECORD
