Metadata-Version: 2.1
Name: saola_graphql_client
Version: 0.0.8
Summary: A Python client for Saola's GraphQL API
Author-email: Saola <support@saola.sg>
Project-URL: Homepage, https://github.com/saola-tech/saola-graphql-client
Project-URL: Issues, https://github.com/saola-tech/saola-graphql-client/issues
Classifier: Programming Language :: Python :: 3
Classifier: License :: OSI Approved :: MIT License
Classifier: Operating System :: OS Independent
Requires-Python: >=3.9
License-File: LICENSE.md
Requires-Dist: ariadne-codegen ==0.12.0
